SETools/__init__.py
SETools/comp.py
SETools/metrics.py
SETools/utils.py
SETools-1.2.3.dist-info/METADATA
SETools-1.2.3.dist-info/RECORD
SETools-1.2.3.dist-info/WHEEL
SETools-1.2.3.dist-info/entry_points.txt
SETools-1.2.3.dist-info/top_level.txt
SETools-1.2.3.dist-info/zip-safe
